requirements.txt
setup.py
django_update_from_dict/__init__.py
django_update_from_dict.egg-info/PKG-INFO
django_update_from_dict.egg-info/SOURCES.txt
django_update_from_dict.egg-info/dependency_links.txt
django_update_from_dict.egg-info/top_level.txt