Metadata-Version: 2.1
Name: django-update-from-dict
Version: 2020.7.1
Summary: Update Django model from dictionary
Home-page: https://github.com/andrewp-as-is/django-update-from-dict.py
License: Unlicense
Keywords: django update dict
Platform: UNKNOWN
Classifier: Framework :: Django
Classifier: License :: Public Domain
Classifier: Operating System :: OS Independent
Classifier: Programming Language :: Python :: 3
